{
    "class": "DepictionTabView",
    "minVersion": "0.4",
    "headerImage": "https://raw.githubusercontent.com/b1atant/Logo/main/header.png",
    "tintColor":"#E94D47",
    "tabs": [
        {
            "class": "DepictionStackView",
            "tabname": "Details",
            "views": [
                {
                    "class": "DepictionButtonView",
                    "text": "Buy Me A ☕️",
                    "action": "https://ko-fi.com/blatant",
                    "openExternal": true,
                    "tintColor": "#E94D47"
                },
                {
                    "class": "DepictionSeparatorView"
                },
                {
                    "class": "DepictionScreenshotsView",
                    "itemCornerRadius": 6,
                    "itemSize": "[160, 346]",
                    "screenshots": [
                        {
                            "accessibilityText": "Screenshot",
                            "url": "https://i.ibb.co/J73670y/IMG-7268.png"
                        },
                        {
                            "accessibilityText": "Screenshot",
                            "url": "https://i.ibb.co/VVZ7FYy/IMG-7269.png"
                        },
                        {
                            "accessibilityText": "Screenshot",
                            "url": "https://i.ibb.co/Tbyzf9V/IMG-7270.png"
                        }
                    ]
                },
                {
                    "class": "DepictionHeaderView",
                    "title": "Description"
                },
                {
                    "class": "DepictionSeparatorView"
                },
                {
                    "class": "DepictionMarkdownView",
                    "markdown": "Unlock's In-App Subscription \n⚠️Disable tweak injection into this app with choicy and only allow KineMaster Tweak or else app will crash  \n⚠️Login to activate subscription",
                    "useSpacing": true
                },
                {
                    "class": "DepictionHeaderView",
                    "title": "Package Info"
                },
                {
                    "class": "DepictionSeparatorView"
                },
                {
                    "class": "DepictionTableTextView",
                    "title": "Version",
                    "text": "1.0"
                },
                {
                    "class": "DepictionTableTextView",
                    "title": "Author",
                    "text": "blatant"
                },
                {
                    "class": "DepictionTableTextView",
                    "title": "Section",
                    "text": "Cracks"
                }
            ]
        },
        {
            "class": "DepictionStackView",
            "tabname": "Changelog",
            "views": [
                {
                    "class": "DepictionSubheaderView",
                    "title": "Version 1.0",
                    "useBoldText": true,
                    "useBottomMargin": false
                },
                {
                    "class": "DepictionMarkdownView",
                    "markdown": "Initial Release",
                    "useSpacing": true
                }
            ]
        }
    ]
}